autopacmen/__init__.py
autopacmen/analysis_fva_comparison.py
autopacmen/analysis_fva_prot_pool.py
autopacmen/data_create_combined_kcat_database.py
autopacmen/data_parse_bigg_metabolites_file.py
autopacmen/data_parse_brenda_json_for_model.py
autopacmen/data_parse_brenda_textfile.py
autopacmen/data_parse_sabio_rk_for_model.py
autopacmen/modeling_create_gecko_model.py
autopacmen/modeling_create_smoment_model.py
autopacmen/modeling_get_initial_spreadsheets.py
autopacmen/modeling_get_protein_mass_mapping.py
autopacmen/modeling_get_reactions_kcat_mapping.py
autopacmen/optimization_apply_manual_changes.py
autopacmen/submodules/__init__.py
autopacmen/submodules/apply_manual_changes.py
autopacmen/submodules/create_combined_kcat_database.py
autopacmen/submodules/create_gecko_model_reaction_wise.py
autopacmen/submodules/create_smoment_model_reaction_wise.py
autopacmen/submodules/fva_comparison.py
autopacmen/submodules/fva_prot_pool.py
autopacmen/submodules/get_differential_reactions.py
autopacmen/submodules/get_initial_spreadsheets.py
autopacmen/submodules/get_protein_mass_mapping.py
autopacmen/submodules/get_reactions_kcat_mapping.py
autopacmen/submodules/helper_create_model.py
autopacmen/submodules/helper_general.py
autopacmen/submodules/kegg.py
autopacmen/submodules/ncbi_taxonomy.py
autopacmen/submodules/parse_bigg_metabolites_file.py
autopacmen/submodules/parse_brenda_json_for_model.py
autopacmen/submodules/parse_brenda_textfile.py
autopacmen/submodules/parse_sabio_rk.py
autopacmen/submodules/parse_sabio_rk_for_model.py
autopacmen/submodules/reaction_flux_control_by_scenario.py
autopacmen_Paulocracy-0.6.3.dist-info/LICENSE
autopacmen_Paulocracy-0.6.3.dist-info/METADATA
autopacmen_Paulocracy-0.6.3.dist-info/WHEEL
autopacmen_Paulocracy-0.6.3.dist-info/entry_points.txt
autopacmen_Paulocracy-0.6.3.dist-info/top_level.txt
autopacmen_Paulocracy-0.6.3.dist-info/RECORD
