Metadata-Version: 2.1
Name: autopacmen-Paulocracy
Version: 0.6.3
Summary: The AutoPACMEN package
Home-page: https://github.com/Paulocracy/autopacmen
Author: Pavlos Stephanos Bekiaris
Author-email: bekiaris@mpi-magdeburg.mpg.de
Project-URL: Homepage, https://github.com/klamt-lab/autopacmen
Project-URL: Issues, https://github.com/klamt-lab/autopacmen/issues
Classifier: Programming Language :: Python :: 3
Classifier: License :: OSI Approved :: Apache Software License
Classifier: Operating System :: OS Independent
Requires-Python: >=3.7
License-File: LICENSE
Requires-Dist: biopython
Requires-Dist: cobra
Requires-Dist: click
Requires-Dist: openpyxl
Requires-Dist: pebble
Requires-Dist: requests
Requires-Dist: xlsxwriter
